LICENSE
README.md
pyproject.toml
setup.cfg
setup.py
tests/test_base.py
tests/test_models.py
tests/test_oauth2.py
zenmoney/__init__.py
zenmoney/base.py
zenmoney/constant.py
zenmoney/exception.py
zenmoney/oauth2.py
zenmoney/request.py
zenmoney/utils.py
zenmoney/models/__init__.py
zenmoney/models/account.py
zenmoney/models/budget.py
zenmoney/models/company.py
zenmoney/models/country.py
zenmoney/models/deletion.py
zenmoney/models/diff.py
zenmoney/models/enums.py
zenmoney/models/instrument.py
zenmoney/models/merchant.py
zenmoney/models/reminder.py
zenmoney/models/reminder_marker.py
zenmoney/models/tag.py
zenmoney/models/token.py
zenmoney/models/transaction.py
zenmoney/models/user.py
zenmoney/models/utils.py
zenmoney_py.egg-info/PKG-INFO
zenmoney_py.egg-info/SOURCES.txt
zenmoney_py.egg-info/dependency_links.txt
zenmoney_py.egg-info/requires.txt
zenmoney_py.egg-info/top_level.txt