Metadata-Version: 2.1
Name: zenmoney-py
Version: 1.0.12
Summary: Library for zenmoney.ru API
Home-page: https://github.com/cooper30/zenmoney_lib.git
Author: Nikita Zvekov
Author-email: cooper30@mail.ru
License: MIT
Platform: UNKNOWN
Classifier: Development Status :: 4 - Beta
Classifier: License :: OSI Approved :: MIT License
Classifier: Environment :: Console
Classifier: Programming Language :: Python :: 3
Classifier: Operating System :: OS Independent
Requires-Python: ~=3.12
License-File: LICENSE
